niwrap_fsl/fsl/__init__.py
niwrap_fsl/fsl/aff2rigid.py
niwrap_fsl/fsl/anatomical_average.py
niwrap_fsl/fsl/applytopup.py
niwrap_fsl/fsl/applywarp.py
niwrap_fsl/fsl/applyxfm4_d.py
niwrap_fsl/fsl/asl_file.py
niwrap_fsl/fsl/asl_mfree.py
niwrap_fsl/fsl/atlasquery.py
niwrap_fsl/fsl/avscale.py
niwrap_fsl/fsl/avw2fsl.py
niwrap_fsl/fsl/b0calc.py
niwrap_fsl/fsl/basil_var.py
niwrap_fsl/fsl/baycest.py
niwrap_fsl/fsl/bedpostx.py
niwrap_fsl/fsl/bedpostx_datacheck.py
niwrap_fsl/fsl/bedpostx_gpu.py
niwrap_fsl/fsl/bet.py
niwrap_fsl/fsl/bet2.py
niwrap_fsl/fsl/betsurf.py
niwrap_fsl/fsl/bianca.py
niwrap_fsl/fsl/bianca_cluster_stats.py
niwrap_fsl/fsl/bianca_overlap_measures.py
niwrap_fsl/fsl/calc_grad_perc_dev.py
niwrap_fsl/fsl/ccops.py
niwrap_fsl/fsl/check_feat.py
niwrap_fsl/fsl/cluster.py
niwrap_fsl/fsl/cluster2html.py
niwrap_fsl/fsl/concat_bvars.py
niwrap_fsl/fsl/connectedcomp.py
niwrap_fsl/fsl/convert_xfm.py
niwrap_fsl/fsl/convertwarp.py
niwrap_fsl/fsl/create_lut.py
niwrap_fsl/fsl/cutoffcalc.py
niwrap_fsl/fsl/design_ttest2.py
niwrap_fsl/fsl/distancemap.py
niwrap_fsl/fsl/dtifit.py
niwrap_fsl/fsl/dtigen.py
niwrap_fsl/fsl/dual_regression.py
niwrap_fsl/fsl/easythresh.py
niwrap_fsl/fsl/eddy.py
niwrap_fsl/fsl/eddy_combine.py
niwrap_fsl/fsl/eddy_correct.py
niwrap_fsl/fsl/eddy_cuda8_0.py
niwrap_fsl/fsl/eddy_cuda9_1.py
niwrap_fsl/fsl/eddy_openmp.py
niwrap_fsl/fsl/eddy_quad.py
niwrap_fsl/fsl/eddy_squad.py
niwrap_fsl/fsl/epi_reg.py
niwrap_fsl/fsl/estnoise.py
niwrap_fsl/fsl/extracttxt.py
niwrap_fsl/fsl/fabber.py
niwrap_fsl/fsl/fabber_asl.py
niwrap_fsl/fsl/fabber_cest.py
niwrap_fsl/fsl/fabber_dce.py
niwrap_fsl/fsl/fabber_dualecho.py
niwrap_fsl/fsl/fabber_dwi.py
niwrap_fsl/fsl/fabber_qbold.py
niwrap_fsl/fsl/fabber_t1.py
niwrap_fsl/fsl/fast.py
niwrap_fsl/fsl/fdr.py
niwrap_fsl/fsl/feat.py
niwrap_fsl/fsl/feat_gm_prepare.py
niwrap_fsl/fsl/feat_model.py
niwrap_fsl/fsl/featquery.py
niwrap_fsl/fsl/featregapply.py
niwrap_fsl/fsl/film_cifti.py
niwrap_fsl/fsl/film_gls.py
niwrap_fsl/fsl/filmbabe.py
niwrap_fsl-0.8.3.dist-info/WHEEL
niwrap_fsl-0.8.3.dist-info/METADATA
niwrap_fsl-0.8.3.dist-info/RECORD
